<?xml version="1.0" encoding="UTF-8"?>
<activity id="2131" moduleid="11212" modulename="label" contextid="86133">
  <label id="2131">
    <name>Collect data using your digital questionnaireConti...</name>
    <intro>&lt;p dir="ltr" style="text-align: left;"&gt;&lt;strong&gt;&lt;/strong&gt;&lt;/p&gt;&lt;strong style="font-size: 0.9375rem;"&gt;Collect data using your digital questionnaire&lt;/strong&gt;&lt;br&gt;&lt;p dir="ltr"&gt;&lt;span&gt;&lt;br&gt;&lt;/span&gt;&lt;/p&gt;&lt;p dir="ltr"&gt;&lt;span id="docs-internal-guid-d4022f5f-7fff-9eb4-3b83-c47208b70a69"&gt;Continue to monitor the quality of data as soon as it is collected. Identifying errors quickly can help you correct them, often by going back to the person interviewed for the questionnaire.&lt;/span&gt;&lt;/p&gt;&lt;br&gt;&lt;p&gt;&lt;/p&gt;</intro>
    <introformat>1</introformat>
    <timemodified>1692581349</timemodified>
  </label>
</activity>